{
  "data": {
    "product": {
      "care_instructions": "<p>Machine wash at 30°. Lorem ipsum dolor sit amet, consectetur adipiscing elit. Ut enim ad minim veniam.</p>",
      "category": "dresses",
      "color_id": "1001",
      "description": "<p>Acme Store Limited Edition • New Arrival</p><br/><p>Long dress in crêpe chiffon with a deep V-neckline and an unlined yoke and batwing sleeves detailed with covered elastication for a ruched effect. Loose fit with a narrow drawstring at the waist with dice-shaped metal beads. Viscose lining.</p>",
      "estimated_delivery_date": "2025-03-24T14:30:45.123Z",
      "target": "ladies",
      "id": "1265383003",
      "images": [
        {
          "alt": "Chain-detail kaftan dress - Rust red - Ladies | 1",
          "height": 3240,
          "url": "https://image.hm.com/assets/hm/25/56/255626d23d880d6585f907874b38016e184ef8a1.jpg?imwidth=2160",
          "width": 2160
        },
        {
          "alt": "Chain-detail kaftan dress - Rust red - Ladies | 2",
          "height": 3240,
          "url": "https://image.hm.com/assets/hm/ee/c4/eec432ac3e4d590cd08631217cdd99fb110088b3.jpg?imwidth=2160",
          "width": 2160
        }
      ],
      "limited_edition": true,
      "materials": "<p>Shell: Lorem ipsum dolor sit amet, consectetur adipiscing elit.</p><br/><p>Lining: Vestibulum ante ipsum primis in faucibus orci luctus et ultrices posuere cubilia Curae;.</p>",
      "new_arrival": false,
      "price": {
        "currency": "£",
        "value": 44.99
      },
      "sale_price": null,
      "title": "Chain-detail kaftan dress",
      "url": "/pdp/chain-detail-kaftan-dress?ct=true&colorId=1001&pid=1265383003",
      "variants": {
        "colors": [
          {
            "id": "1001",
            "image": {
              "alt": "Rust red",
              "height": 174,
              "url": "https://image.hm.com/assets/hm/25/56/255626d23d880d6585f907874b38016e184ef8a1.jpg?imwidth=116",
              "width": 116
            },
            "name": "Rust red",
            "sizes": [
              {
                "id": "001",
                "name": "XS-S",
                "quantity": 0
              },
              {
                "id": "002",
                "name": "M-L",
                "quantity": 0
              },
              {
                "id": "003",
                "name": "XL-XXL",
                "quantity": 0
              }
            ],
            "url": "/pdp/chain-detail-kaftan-dress?ct=true&colorId=1001&pid=1265383003",
            "value": "#b7410e"
          }
        ]
      }
    }
  }
}
